NosqlShujukuRumenjiaochengCYuyanBianchengWang/README.md
NosqlShujukuRumenjiaochengCYuyanBianchengWang/__init__.py
NosqlShujukuRumenjiaochengCYuyanBianchengWang/__main__.py
NosqlShujukuRumenjiaochengCYuyanBianchengWang/file.epub
NosqlShujukuRumenjiaochengCYuyanBianchengWang/index.html
NosqlShujukuRumenjiaochengCYuyanBianchengWang/css/__init__.py
NosqlShujukuRumenjiaochengCYuyanBianchengWang/css/annotations.css
NosqlShujukuRumenjiaochengCYuyanBianchengWang/css/main.css
NosqlShujukuRumenjiaochengCYuyanBianchengWang/css/normalize.css
NosqlShujukuRumenjiaochengCYuyanBianchengWang/css/popup.css
NosqlShujukuRumenjiaochengCYuyanBianchengWang/font/__init__.py
NosqlShujukuRumenjiaochengCYuyanBianchengWang/font/fontello.eot
NosqlShujukuRumenjiaochengCYuyanBianchengWang/font/fontello.svg
NosqlShujukuRumenjiaochengCYuyanBianchengWang/font/fontello.ttf
NosqlShujukuRumenjiaochengCYuyanBianchengWang/font/fontello.woff
NosqlShujukuRumenjiaochengCYuyanBianchengWang/img/__init__.py
NosqlShujukuRumenjiaochengCYuyanBianchengWang/img/annotator-glyph-sprite.png
NosqlShujukuRumenjiaochengCYuyanBianchengWang/img/annotator-icon-sprite.png
NosqlShujukuRumenjiaochengCYuyanBianchengWang/img/apple-touch-icon.png
NosqlShujukuRumenjiaochengCYuyanBianchengWang/img/cancelfullscreen.png
NosqlShujukuRumenjiaochengCYuyanBianchengWang/img/close.png
NosqlShujukuRumenjiaochengCYuyanBianchengWang/img/fullscreen.png
NosqlShujukuRumenjiaochengCYuyanBianchengWang/img/loader.gif
NosqlShujukuRumenjiaochengCYuyanBianchengWang/img/menu-icon.png
NosqlShujukuRumenjiaochengCYuyanBianchengWang/img/save.png
NosqlShujukuRumenjiaochengCYuyanBianchengWang/img/saved.png
NosqlShujukuRumenjiaochengCYuyanBianchengWang/img/settings-s.png
NosqlShujukuRumenjiaochengCYuyanBianchengWang/img/settings.png
NosqlShujukuRumenjiaochengCYuyanBianchengWang/img/star.png
NosqlShujukuRumenjiaochengCYuyanBianchengWang/js/__init__.py
NosqlShujukuRumenjiaochengCYuyanBianchengWang/js/epub.js
nosql_shujuku_rumenjiaocheng_c_yuyan_biancheng_wang-2024.3.5.0.dist-info/METADATA
nosql_shujuku_rumenjiaocheng_c_yuyan_biancheng_wang-2024.3.5.0.dist-info/WHEEL
nosql_shujuku_rumenjiaocheng_c_yuyan_biancheng_wang-2024.3.5.0.dist-info/entry_points.txt
nosql_shujuku_rumenjiaocheng_c_yuyan_biancheng_wang-2024.3.5.0.dist-info/top_level.txt
nosql_shujuku_rumenjiaocheng_c_yuyan_biancheng_wang-2024.3.5.0.dist-info/RECORD
